sqlalchemy_query_helpers/__init__.py
sqlalchemy_query_helpers/main.py
sqlalchemy_query_helpers-1.0.107.dist-info/licenses/LICENSE
sqlalchemy_query_helpers-1.0.107.dist-info/METADATA
sqlalchemy_query_helpers-1.0.107.dist-info/WHEEL
sqlalchemy_query_helpers-1.0.107.dist-info/top_level.txt
sqlalchemy_query_helpers-1.0.107.dist-info/RECORD
