Metadata-Version: 2.4
Name: sqlalchemy-query-helpers
Version: 1.0.107
Summary: Some helpers for SQLAlchemy
Author-email: vladiscripts <blagopoluchie12@gmail.com>
Project-URL: Homepage, https://github.com/vladiscripts/sqlalchemy-query-helpers
Project-URL: Issues, https://github.com/vladiscripts/sqlalchemy-query-helpers/issues
Classifier: Programming Language :: Python :: 3
Classifier: License :: OSI Approved :: MIT License
Classifier: Operating System :: OS Independent
Requires-Python: >=3.10
License-File: LICENSE
Requires-Dist: sqlalchemy
Dynamic: license-file
